fastai_xla_extensions/__init__.py
fastai_xla_extensions/_nbdev.py
fastai_xla_extensions/all.py
fastai_xla_extensions/cifar_loader.py
fastai_xla_extensions/core.py
fastai_xla_extensions/dev_setup.py
fastai_xla_extensions/misc_utils.py
fastai_xla_extensions/utils.py
fastai_xla_extensions/multi_core/__init__.py
fastai_xla_extensions/multi_core/base.py
fastai_xla_extensions/multi_core/callback.py
fastai_xla_extensions/multi_core/inference.py
fastai_xla_extensions/multi_core/learner.py
fastai_xla_extensions/multi_core/lr_find.py
fastai_xla_extensions/multi_core/torch_compat.py
fastai_xla_extensions-0.0.12.dist-info/LICENSE
fastai_xla_extensions-0.0.12.dist-info/METADATA
fastai_xla_extensions-0.0.12.dist-info/WHEEL
fastai_xla_extensions-0.0.12.dist-info/entry_points.txt
fastai_xla_extensions-0.0.12.dist-info/top_level.txt
fastai_xla_extensions-0.0.12.dist-info/RECORD
