Metadata-Version: 2.1
Name: fastai-xla-extensions
Version: 0.0.12
Summary: A library to extend fastai to run on TPUs using pytorch-xla
Home-page: https://github.com/butchland/fastai_xla_extensions/tree/master/
Author: Butch Landingin
Author-email: butchland@gmail.com
License: Apache Software License 2.0
Keywords: fastai pytorch pytorch-xla tpu
Platform: UNKNOWN
Classifier: Development Status :: 3 - Alpha
Classifier: Intended Audience :: Developers
Classifier: License :: OSI Approved :: Apache Software License
Classifier: Natural Language :: English
Classifier: Programming Language :: Python :: 3.6
Classifier: Programming Language :: Python :: 3.7
Classifier: Programming Language :: Python :: 3.8
Requires-Python: >=3.6
Requires-Dist: fastai (==2.3.0)
